soaper/__init__.py
soaper-0.1.dist-info/METADATA
soaper-0.1.dist-info/RECORD
soaper-0.1.dist-info/WHEEL
soaper-0.1.dist-info/top_level.txt
