Metadata-Version: 2.1
Name: soaper
Version: 0.1
Summary: soap data parser
Home-page: https://github.com/Jisu9921/soaper
Author: Jisu9921
Author-email: h41469921@gmail.com
License: UNKNOWN
Platform: UNKNOWN
Classifier: Programming Language :: Python :: 3.6
